lunchkey/__init__.py
lunchkey/main.py
lunchkey-0.1.0.dist-info/licenses/LICENSE
lunchkey-0.1.0.dist-info/METADATA
lunchkey-0.1.0.dist-info/WHEEL
lunchkey-0.1.0.dist-info/entry_points.txt
lunchkey-0.1.0.dist-info/top_level.txt
lunchkey-0.1.0.dist-info/RECORD
