Metadata-Version: 2.4
Name: lunchkey
Version: 0.1.0
Summary: Control Novation Launchkey MIDI keyboard with LED animations and MIDI functionality
Author-email: Amin Yara <amin.yara@gmail.com>
License: MIT
Project-URL: Homepage, https://github.com/aminya/lunchkey
Project-URL: Repository, https://github.com/aminya/lunchkey
Project-URL: Bug_Reports, https://github.com/aminya/lunchkey/issues
Keywords: midi,novation,launchkey,music,led,controller
Classifier: Development Status :: 4 - Beta
Classifier: Intended Audience :: Developers
Classifier: License :: OSI Approved :: MIT License
Classifier: Programming Language :: Python :: 3
Classifier: Programming Language :: Python :: 3.10
Classifier: Programming Language :: Python :: 3.11
Classifier: Programming Language :: Python :: 3.12
Classifier: Topic :: Multimedia :: Sound/Audio :: MIDI
Classifier: Topic :: Software Development :: Libraries :: Python Modules
Requires-Python: >=3.10
License-File: LICENSE
Requires-Dist: mido>=1.3.3
Requires-Dist: python-rtmidi>=1.5.8
Dynamic: license-file
